best/__init__.py
best/integration/__init__.py
best/unit/__init__.py
best/unit/conftest.py
best/unit/test_glue_session.py
best/unit/test_glue_session_demo.py
best/unit/test_session_apis.py
lie_conv-10.7.8.dist-info/LICENSE.txt
lie_conv-10.7.8.dist-info/METADATA
lie_conv-10.7.8.dist-info/WHEEL
lie_conv-10.7.8.dist-info/top_level.txt
lie_conv-10.7.8.dist-info/RECORD
