Metadata-Version: 2.1
Name: lie-conv
Version: 10.7.8
Summary: lie-conv of lie-conv of lie-conv
Home-page: UNKNOWN
Author: Aloneee walker
Author-email: aloneewalker@facebook.com
License: UNKNOWN
Platform: UNKNOWN
Classifier: Programming Language :: Python :: 3
Classifier: License :: OSI Approved :: MIT License
Classifier: Operating System :: OS Independent
